__init__.py
nystrom_ncut/__init__.py
nystrom_ncut/common.py
nystrom_ncut/distance_utils.py
nystrom_ncut/global_settings.py
nystrom_ncut/sampling_utils.py
nystrom_ncut/visualize_utils.py
nystrom_ncut/kernel/__init__.py
nystrom_ncut/kernel/kernel_ncut.py
nystrom_ncut/nystrom/__init__.py
nystrom_ncut/nystrom/distance_realization.py
nystrom_ncut/nystrom/normalized_cut.py
nystrom_ncut/nystrom/nystrom_utils.py
nystrom_ncut/transformer/__init__.py
nystrom_ncut/transformer/axis_align.py
nystrom_ncut/transformer/transformer_mixin.py
nystrom_ncut-0.3.7.dist-info/licenses/LICENSE
nystrom_ncut-0.3.7.dist-info/METADATA
nystrom_ncut-0.3.7.dist-info/WHEEL
nystrom_ncut-0.3.7.dist-info/top_level.txt
nystrom_ncut-0.3.7.dist-info/RECORD
